svarascala/__init__.py
svarascala/__main__.py
svarascala/indian.py
svarascala/modes.py
svarascala/navarasa.py
svarascala/western.py
tests/__init__.py
tests/conftest.py
tests/test_indian.py
tests/test_indian_advanced.py
tests/test_init.py
tests/test_main.py
tests/test_main_advanced.py
tests/test_modes.py
tests/test_navarasa.py
tests/test_navarasa_cli.py
tests/test_suite.py
tests/test_western.py
tests/test_western_advanced.py
svarascala-1.1.0.dist-info/LICENSE
svarascala-1.1.0.dist-info/METADATA
svarascala-1.1.0.dist-info/WHEEL
svarascala-1.1.0.dist-info/entry_points.txt
svarascala-1.1.0.dist-info/top_level.txt
svarascala-1.1.0.dist-info/RECORD
